src/__init__.py
src/recording_times_generator.py
src/sound_extraction.py
sound_extraction-2.1.2.dist-info/LICENSE.txt
sound_extraction-2.1.2.dist-info/METADATA
sound_extraction-2.1.2.dist-info/WHEEL
sound_extraction-2.1.2.dist-info/entry_points.txt
sound_extraction-2.1.2.dist-info/top_level.txt
sound_extraction-2.1.2.dist-info/RECORD
