Metadata-Version: 2.1
Name: sound-extraction
Version: 2.1.2
Home-page: https://github.com/prayagnshah/Sound-Extraction
Author: Prayag Shah
Author-email: prayagshah07@gmail.com
Classifier: Programming Language :: Python :: 3.8
Classifier: Programming Language :: Python :: 3.9
Classifier: Programming Language :: Python :: 3.10
Classifier: License :: OSI Approved :: MIT License
Classifier: Operating System :: OS Independent
License-File: LICENSE.txt
Requires-Dist: certifi (==2023.5.7)
Requires-Dist: cffi (==1.15.1)
Requires-Dist: load-dotenv (==0.1.0)
Requires-Dist: numpy (==1.24.3)
Requires-Dist: pycparser (==2.21)
Requires-Dist: python-dotenv (==1.0.0)
Requires-Dist: sentry-sdk (==1.25.1)
Requires-Dist: soundfile (==0.12.1)
Requires-Dist: urllib3 (==2.0.3)
Requires-Dist: astral (==3.2)
Requires-Dist: backports.zoneinfo (==0.2.1)
Requires-Dist: pytz (==2023.3)
Requires-Dist: tzdata (==2023.3)
